setup.py
hawamaan/__init__.py
hawamaan/hawamaan.py
hawamaan.egg-info/PKG-INFO
hawamaan.egg-info/SOURCES.txt
hawamaan.egg-info/dependency_links.txt
hawamaan.egg-info/requires.txt
hawamaan.egg-info/top_level.txt