Metadata-Version: 1.1
Name: hawamaan
Version: 2.1.0
Summary: Weather forecast data
Home-page: https://github.com/CloudFoundry276/WeatherForecastLibrary
Author: Sagar Pitalekar
Author-email: pypi.cloudfoundry276@gmail.com
License: MIT
Keywords: weather,forecast,openweather
Platform: UNKNOWN
Classifier: Development Status :: 3 - Alpha
Classifier: Intended Audience :: Developers
Classifier: Topic :: Software Development :: Build Tools
Classifier: License :: OSI Approved :: MIT License
Classifier: Programming Language :: Python :: 3.5
Classifier: Programming Language :: Python :: 3.6
Classifier: Programming Language :: Python :: 3.7
Classifier: Programming Language :: Python :: 3.8
